xdagtool/__init__.py
xdagtool/xdu.py
xdagtool/xdu_test.py
xdagtool-0.4.dist-info/LICENSE
xdagtool-0.4.dist-info/METADATA
xdagtool-0.4.dist-info/WHEEL
xdagtool-0.4.dist-info/entry_points.txt
xdagtool-0.4.dist-info/top_level.txt
xdagtool-0.4.dist-info/RECORD
