Metadata-Version: 2.1
Name: xdagtool
Version: 0.4
Summary: Xdag slicing tool
Home-page: https://github.com/rulerson/xdagtool
Author: Larry Wu
Author-email: rulerson@qq.com
License: UNKNOWN
Keywords: xdag
Platform: UNKNOWN
Classifier: Programming Language :: Python :: 3
Classifier: License :: OSI Approved :: MIT License
Classifier: Operating System :: OS Independent
Requires-Python: >=3.7
Requires-Dist: python-dateutil
Requires-Dist: click
